safe_netrc/__init__.py
safe_netrc/_version.py
safe_netrc/tests/__init__.py
safe_netrc/tests/test_safe_netrc.py
safe_netrc-1.0.1.dist-info/LICENSE.md
safe_netrc-1.0.1.dist-info/METADATA
safe_netrc-1.0.1.dist-info/WHEEL
safe_netrc-1.0.1.dist-info/top_level.txt
safe_netrc-1.0.1.dist-info/RECORD
