Metadata-Version: 2.1
Name: safe-netrc
Version: 1.0.1
Summary: Safe netrc file parser
Author-email: Leo Singer <leo.p.singer@nasa.gov>
License: GPL-2.0-or-later
Project-URL: source, https://git.ligo.org/computing/safe-netrc
Project-URL: Bug Tracker, https://git.ligo.org/computing/safe-netrc/issues
Classifier: Development Status :: 5 - Production/Stable
Classifier: Environment :: Console
Classifier: License :: OSI Approved :: GNU General Public License v2 or later (GPLv2+)
Classifier: Operating System :: POSIX
Classifier: Programming Language :: Python :: 3
Classifier: Programming Language :: Python :: 3.7
Classifier: Programming Language :: Python :: 3.8
Classifier: Programming Language :: Python :: 3.9
Classifier: Programming Language :: Python :: 3.10
Classifier: Programming Language :: Python :: 3.11
Classifier: Topic :: Internet
Classifier: Topic :: Security
Requires-Python: >=3.7
Provides-Extra: test
License-File: LICENSE.md
